CHANGELOG.txt
README.md
setup.py
./pipgeoip/GeoLite2-ASN.mmdb
./pipgeoip/GeoLite2-City.mmdb
pipgeoip/__init__.py
pipgeoip.egg-info/PKG-INFO
pipgeoip.egg-info/SOURCES.txt
pipgeoip.egg-info/dependency_links.txt
pipgeoip.egg-info/not-zip-safe
pipgeoip.egg-info/requires.txt
pipgeoip.egg-info/top_level.txt