Metadata-Version: 2.1
Name: pipgeoip
Version: 1.0.2
Summary: Python GeoIP
Home-page: https://himelrana.com
Author: Himel
Author-email: contact@himelrana.com
License: MIT
Keywords: geoip,ipinfo,ip2info,ip information,ip to location,ip location
Platform: UNKNOWN
Classifier: Development Status :: 5 - Production/Stable
Classifier: Intended Audience :: Developers
Classifier: Operating System :: Microsoft :: Windows :: Windows 10
Classifier: License :: OSI Approved :: MIT License
Classifier: Programming Language :: Python :: 3
Requires-Python: >=3.6
